main.py
sub_main.py
helloworld_noufal16-0.0.1.dist-info/METADATA
helloworld_noufal16-0.0.1.dist-info/WHEEL
helloworld_noufal16-0.0.1.dist-info/top_level.txt
helloworld_noufal16-0.0.1.dist-info/RECORD
